README.md
setup.py
docker_cron/__init__.py
docker_cron_cli.egg-info/PKG-INFO
docker_cron_cli.egg-info/SOURCES.txt
docker_cron_cli.egg-info/dependency_links.txt
docker_cron_cli.egg-info/entry_points.txt
docker_cron_cli.egg-info/requires.txt
docker_cron_cli.egg-info/top_level.txt